meteortools/fileformats/UFOAnalyzerXML.py
meteortools/fileformats/UFOCapXML.py
meteortools/fileformats/__init__.py
meteortools/fileformats/ftpDetectInfo.py
meteortools/fileformats/imoWorkingShowerList.py
meteortools/fileformats/kmlHandlers.py
meteortools/fileformats/platepar.py
meteortools/rmsutils/__init__.py
meteortools/rmsutils/analyseUFOwithRMS.py
meteortools/rmsutils/multiDayRadiant.py
meteortools/rmsutils/multiEventGroundMap.py
meteortools/rmsutils/multiTrackStack.py
meteortools/rmsutils/pickleToKml.py
meteortools/rmsutils/plotCAMSOrbits.py
meteortools/rmsutils/plotRMSOrbits.py
meteortools/share/IMO_Working_Meteor_Shower_List.xml
meteortools/share/__init__.py
meteortools/share/gmn_shower_table_20230518.npy
meteortools/share/streamfulldata.npy
meteortools/ukmondb/ECSVhandler.py
meteortools/ukmondb/__init__.py
meteortools/ukmondb/getDetections.py
meteortools/ukmondb/getLiveImages.py
meteortools/ukmondb/getMatches.py
meteortools/ukmondb/trajPickle.py
meteortools/ukmondb/trajectoryKML.py
meteortools/utils/Math.py
meteortools/utils/VectorMaths.py
meteortools/utils/__init__.py
meteortools/utils/annotateImage.py
meteortools/utils/convertSolLon.py
meteortools/utils/drawFTPfile.py
meteortools/utils/findNearDuplicates.py
meteortools/utils/getActiveShowers.py
meteortools/utils/getOverlappingFovs.py
meteortools/utils/getRiseSet.py
meteortools/utils/getShowerDates.py
meteortools/utils/plotTrack.py
meteortools/utils/sendAnEmail.py
MeteorTools-2024.1.0.dist-info/LICENSE
MeteorTools-2024.1.0.dist-info/METADATA
MeteorTools-2024.1.0.dist-info/WHEEL
MeteorTools-2024.1.0.dist-info/top_level.txt
MeteorTools-2024.1.0.dist-info/RECORD
