Metadata-Version: 2.1
Name: MeteorTools
Version: 2024.1.0
Summary: Python Tools for Meteor Data Analysis
Author-email: Mark McIntyre <markmcintyre99@googlemail.com>
License: GNU GENERAL PUBLIC LICENSE
Project-URL: Homepage, https://markmac99.github.io/MeteorTools/
Project-URL: Bug Tracker, https://github.com/markmac99/MeteorTools/issues
Keywords: meteors,ukmon
Classifier: Programming Language :: Python
Classifier: Programming Language :: Python :: 3
Classifier: Intended Audience :: Science/Research
Classifier: Topic :: Scientific/Engineering :: Astronomy
Requires-Python: >=3.7
License-File: LICENSE
Requires-Dist: fastparquet
Requires-Dist: google-auth
Requires-Dist: google-auth-oauthlib
Requires-Dist: google-api-python-client
Requires-Dist: googleapis-common-protos
Requires-Dist: numpy
Requires-Dist: oauthlib
Requires-Dist: pandas
Requires-Dist: Pillow
Requires-Dist: pytz
Requires-Dist: Shapely
Requires-Dist: simplekml
Requires-Dist: s3fs
Requires-Dist: xmltodict
Requires-Dist: requests
Requires-Dist: pdoc
Requires-Dist: Cython
Requires-Dist: imageio
Requires-Dist: scipy
Requires-Dist: jplephem
Requires-Dist: pyephem
Requires-Dist: gitpython
Requires-Dist: astropy
Requires-Dist: basemap
Requires-Dist: basemap-data-hires
Requires-Dist: pyqt5 ; platform_machine != "aarch64" and platform_machine != "armv7l"
Requires-Dist: opencv-python ; platform_machine != "armv7l"
Requires-Dist: pyproj ==2.6.1.post1 ; python_version < "3.8" and platform_machine != "armv7l"
Requires-Dist: pyproj ==1.9.6 ; python_version < "3.8" and platform_machine == "armv7l"
Requires-Dist: matplotlib ==3.3.2 ; python_version <= "3.8" and platform_machine != "aarch64"
Requires-Dist: matplotlib ; python_version > "3.8" or platform_machine == "aarch64"
Requires-Dist: pyproj ==3.5.0 ; python_version >= "3.8"
Provides-Extra: dev
Requires-Dist: bumpver ; extra == 'dev'
Requires-Dist: gitpython ; extra == 'dev'
Requires-Dist: behave ; extra == 'dev'
Requires-Dist: pytest ; extra == 'dev'
Requires-Dist: pip-tools ; extra == 'dev'
